langgraph_checkpoint_datastore/__init__.py
langgraph_checkpoint_datastore/saver.py
langgraph_checkpoint_datastore/write.py
langgraph_checkpoint_datastore-0.1.0.dist-info/LICENCE
langgraph_checkpoint_datastore-0.1.0.dist-info/METADATA
langgraph_checkpoint_datastore-0.1.0.dist-info/WHEEL
langgraph_checkpoint_datastore-0.1.0.dist-info/top_level.txt
langgraph_checkpoint_datastore-0.1.0.dist-info/RECORD
