Metadata-Version: 2.2
Name: langgraph_checkpoint_datastore
Version: 0.1.0
Summary: Datstore Saver for LangGraph Checkpoints
Home-page: https://github.com/rynmccrmck/langgraph-checkpoint-datstore
Author: Ryan McCormack
Author-email: ryan@sardine.ai
Classifier: Programming Language :: Python :: 3
Classifier: Operating System :: OS Independent
Requires-Python: >=3.6
License-File: LICENCE
Requires-Dist: boto3>=1.17.0
Requires-Dist: langchain>=0.3.9
Requires-Dist: langgraph>=0.2.53
Dynamic: author
Dynamic: author-email
Dynamic: classifier
Dynamic: description
Dynamic: description-content-type
Dynamic: home-page
Dynamic: requires-dist
Dynamic: requires-python
Dynamic: summary
